{"is_source_file": true, "format": "Markdown", "description": "This file provides detailed documentation and configuration instructions for integrating Supabase services (Authentication, Storage, and Database) into a frontend application. It explains environment setup, storage policies, database schema, authentication flows, and troubleshooting steps, serving as a comprehensive setup guide rather than executable source code.", "external_files": ["src/lib/supabaseClient.js", "src/pages/AuthCallback.jsx", "src/pages/AuthPage.jsx", "src/pages/Dashboard.jsx", "src/components/UploadModal.jsx"], "external_methods": ["storage.getPublicUrl()", "supabase.auth.getSessionFromUrl()"], "published": [], "classes": [], "methods": [], "calls": [], "search-terms": ["Supabase", "storage policies", "database schema", "auth redirects", "environment variables", "public.notes table", "supabaseClient.js", "AuthCallback", "UploadModal", "Dashboard"], "state": 2, "file_id": 16, "knowledge_revision": 63, "git_revision": "123c4cf114c3dc4b1e8462e55defae6b4d04f2ba", "hash": "dfd26b4adae41206af08d1a3a683ed6d", "format-version": 4, "code-base-name": "react_frontend", "filename": "assets/supabase.md", "revision_history": [{"63": "123c4cf114c3dc4b1e8462e55defae6b4d04f2ba"}]}