{"is_source_file": true, "format": "JavaScript (React JSX)", "description": "This file defines a React functional component 'Navbar' responsible for rendering a navigation bar with branding, search, category filter, and user action buttons, including handling URL sync, user session management, and interactions with external services (like supabase for authentication).", "external_files": ["../lib/supabaseClient", "react", "react-router-dom"], "external_methods": ["supabase.auth.signOut", "useEffect", "useId", "useState", "useLocation", "useNavigate", "useSearchParams", "Link"], "published": ["Navbar"], "classes": [], "methods": [{"name": "Navbar({ session, onUpload })", "description": "React component rendering navigation bar with branding, search, filters, and user actions.", "scope": "", "scopeKind": ""}], "calls": ["supabase.auth.signOut", "setQ", "setCat", "setSearchParams", "navigate", "useEffect", "buildParams", "onSubmit", "onCategoryChange", "setQ", "setCat"], "search-terms": ["Navbar", "react-router-dom", "supabase", "search input", "category filter", "navigation bar", "auth sign out", "useState hook", "useEffect hook"], "state": 2, "file_id": 15, "knowledge_revision": 144, "git_revision": "1937c8b7997d0882c8e4f5e113ae6c7d7451a122", "revision_history": [{"33": ""}, {"50": "36dcc7ca3daf4a85ff7daba921233003e2dba613"}, {"67": "74146be694019635d59951730c72f57fe2dd6231"}, {"72": "39af8d858c655b7b283d74e9c3a0d72d6a6fd161"}, {"82": "39af8d858c655b7b283d74e9c3a0d72d6a6fd161"}, {"83": "39af8d858c655b7b283d74e9c3a0d72d6a6fd161"}, {"84": "39af8d858c655b7b283d74e9c3a0d72d6a6fd161"}, {"85": "39af8d858c655b7b283d74e9c3a0d72d6a6fd161"}, {"86": "f61f4c1dbb3e467600f9d7a2bd22628b5454a816"}, {"87": "f61f4c1dbb3e467600f9d7a2bd22628b5454a816"}, {"88": "f61f4c1dbb3e467600f9d7a2bd22628b5454a816"}, {"89": "f61f4c1dbb3e467600f9d7a2bd22628b5454a816"}, {"90": "f61f4c1dbb3e467600f9d7a2bd22628b5454a816"}, {"98": "501bbf7c644fe6203b2e8daefdb744ddd9298475"}, {"130": "0c9bbb77bbf545138be3ecb81416c2e7549c2f85"}, {"144": "1937c8b7997d0882c8e4f5e113ae6c7d7451a122"}], "ctags": [{"_type": "tag", "name": "${searchInputId}-desc", "path": "/home/kavia/workspace/code-generation/noteshare-platform-89298-89307/react_frontend/src/components/Navbar.jsx", "pattern": "/^              aria-describedby={`${searchInputId}-desc`}$/", "language": "JavaScript", "kind": "field", "scope": "Navbar.aria", "scopeKind": "class"}, {"_type": "tag", "name": "Navbar", "path": "/home/kavia/workspace/code-generation/noteshare-platform-89298-89307/react_frontend/src/components/Navbar.jsx", "pattern": "/^export default function Navbar({ session, onUpload }) {$/", "language": "JavaScript", "kind": "function", "signature": "({ session, onUpload })"}, {"_type": "tag", "name": "cat", "path": "/home/kavia/workspace/code-generation/noteshare-platform-89298-89307/react_frontend/src/components/Navbar.jsx", "pattern": "/^              value={cat}$/", "language": "JavaScript", "kind": "field", "scope": "Navbar.value", "scopeKind": "class"}, {"_type": "tag", "name": "categorySelectId", "path": "/home/kavia/workspace/code-generation/noteshare-platform-89298-89307/react_frontend/src/components/Navbar.jsx", "pattern": "/^              id={categorySelectId}$/", "language": "JavaScript", "kind": "field", "scope": "Navbar.id", "scopeKind": "class"}, {"_type": "tag", "name": "onSubmit", "path": "/home/kavia/workspace/code-generation/noteshare-platform-89298-89307/react_frontend/src/components/Navbar.jsx", "pattern": "/^          onSubmit={onSubmit}$/", "language": "JavaScript", "kind": "field", "scope": "Navbar.onSubmit", "scopeKind": "class"}, {"_type": "tag", "name": "onUpload", "path": "/home/kavia/workspace/code-generation/noteshare-platform-89298-89307/react_frontend/src/components/Navbar.jsx", "pattern": "/^            onClick={onUpload}$/", "language": "JavaScript", "kind": "field", "scope": "Navbar.onClick", "scopeKind": "class"}, {"_type": "tag", "name": "q", "path": "/home/kavia/workspace/code-generation/noteshare-platform-89298-89307/react_frontend/src/components/Navbar.jsx", "pattern": "/^              value={q}$/", "language": "JavaScript", "kind": "field", "scope": "Navbar.value", "scopeKind": "class"}, {"_type": "tag", "name": "searchInputId", "path": "/home/kavia/workspace/code-generation/noteshare-platform-89298-89307/react_frontend/src/components/Navbar.jsx", "pattern": "/^              id={searchInputId}$/", "language": "JavaScript", "kind": "field", "scope": "Navbar.id", "scopeKind": "class"}], "hash": "d96f2778640b66f87ae538082a3c0fc8", "format-version": 4, "code-base-name": "react_frontend", "filename": "react_frontend/src/components/Navbar.jsx", "fields": [{"name": "aria-describedby={`${searchInputId}-desc`}", "scope": "Navbar.aria", "scopeKind": "class", "description": "unavailable"}, {"name": "value={cat}", "scope": "Navbar.value", "scopeKind": "class", "description": "unavailable"}, {"name": "id={categorySelectId}", "scope": "Navbar.id", "scopeKind": "class", "description": "unavailable"}, {"name": "onSubmit={onSubmit}", "scope": "Navbar.onSubmit", "scopeKind": "class", "description": "unavailable"}, {"name": "onClick={onUpload}", "scope": "Navbar.onClick", "scopeKind": "class", "description": "unavailable"}, {"name": "value={q}", "scope": "Navbar.value", "scopeKind": "class", "description": "unavailable"}, {"name": "id={searchInputId}", "scope": "Navbar.id", "scopeKind": "class", "description": "unavailable"}]}