{"is_source_file": true, "format": "JavaScript (React JSX)", "description": "This file defines a React functional component named PreviewPage which fetches a note by its ID from a database and presents a PDF preview or an appropriate message if unavailable. It manages URL validation, accessibility, and fetch status to provide a user-friendly note preview page.", "external_files": ["../lib/supabaseClient", "react", "react-router-dom"], "external_methods": ["supabase.from", "useParams", "useEffect", "useMemo", "useState", "fetch"], "published": [], "classes": [], "methods": [{"name": "PreviewPage()", "description": "Main React functional component that loads and displays a PDF note based on URL parameters.", "scope": "", "scopeKind": ""}], "calls": ["supabase.from('notes').select('*').eq('id', id).single()", "useParams()", "useEffect(...)", "useMemo(...)", "useState(...)", "fetch(note.public_url, { method: 'GET', mode: 'no-cors', signal: controller.signal })"], "search-terms": ["PreviewPage", "PDF preview", "React note viewer", "Supabase fetch note", "URL validation", "public_url"], "state": 2, "file_id": 25, "knowledge_revision": 61, "git_revision": "", "ctags": [{"_type": "tag", "name": "PreviewPage", "path": "/home/kavia/workspace/code-generation/noteshare-platform-89298-89307/react_frontend/src/pages/PreviewPage.jsx", "pattern": "/^export default function PreviewPage() {$/", "language": "JavaScript", "kind": "function", "signature": "()"}, {"_type": "tag", "name": "note", "path": "/home/kavia/workspace/code-generation/noteshare-platform-89298-89307/react_frontend/src/pages/PreviewPage.jsx", "pattern": "/^            href={note.public_url || '#'}$/", "language": "JavaScript", "kind": "field", "scope": "PreviewPage.href", "scopeKind": "class"}], "hash": "d0066158b47ac653445d364d9cbaa4be", "format-version": 4, "code-base-name": "react_frontend", "filename": "react_frontend/src/pages/PreviewPage.jsx", "fields": [{"name": "href={note.public_url || '#'}", "scope": "PreviewPage.href", "scopeKind": "class", "description": "unavailable"}], "revision_history": [{"61": ""}]}